SumWenhuiZ/__init__.py
SumWenhuiZ/sumPython.py
SumWHZhang-0.1.dist-info/METADATA
SumWHZhang-0.1.dist-info/WHEEL
SumWHZhang-0.1.dist-info/top_level.txt
SumWHZhang-0.1.dist-info/RECORD
