Metadata-Version: 2.1
Name: SumWHZhang
Version: 0.1
Summary: calculate the sum of n numbers from 1 to n
Home-page: UNKNOWN
Author: WenhuiZ
Author-email: UNKNOWN
License: UNKNOWN
Platform: UNKNOWN
